tabaka.py
tabaka_mcp-0.1.2.dist-info/METADATA
tabaka_mcp-0.1.2.dist-info/WHEEL
tabaka_mcp-0.1.2.dist-info/entry_points.txt
tabaka_mcp-0.1.2.dist-info/top_level.txt
tabaka_mcp-0.1.2.dist-info/RECORD
