Metadata-Version: 2.2
Name: tabaka-mcp
Version: 0.1.2
Summary: Add your description here
Requires-Python: >=3.13
Requires-Dist: httpx>=0.28.1
Requires-Dist: mcp[cli]>=1.3.0
Requires-Dist: tabaka-core>=0.0.3
